{
    "behavior": "",
    "checkable": false,
    "class": "h1",
    "clickable": true,
    "content-desc": "",
    "enabled": true,
    "focusable": true,
    "focused": false,
    "hash": "kNYDGkFMWtX4P/QgrgMX0w==\n",
    "height": 30,
    "hier_level": 0,
    "human_hash": "h1_X660_Y240_W600_H30",
    "human_readable": "h1_660_240_600_30_h1_ffffffffffff7fff6dff65ff00ff00ff00ff00ff01ff00ff00ffffffffffffff_72ccfa32311b9d53e3565b339cb4207a",
    "image_path": "ZDJhYmM3OGU3MGUwYzI3NTk3MWFkODcxZjFiNDA1YTc.png",
    "index": -1,
    "internal": {
        "elem_dict": {
            "attributes": {
                "jstcache": "0"
            },
            "backend_node_id": 981,
            "flags": {
                "checkable": false,
                "clickable": true,
                "enabled": true,
                "focusable": true,
                "focused": false,
                "scrollable": false
            },
            "height": 30.0,
            "key": "660_240_600_30_This site can\u2019t be reached",
            "tagName": "h1",
            "text": "This site can\u2019t be reached",
            "width": 600.0,
            "x": 660.0,
            "y": 240.0
        },
        "location": {
            "x": 660.0,
            "y": 240.0
        },
        "size": {
            "height": 30.0,
            "width": 600.0
        },
        "tag_name": "h1",
        "text": "This site can\u2019t be reached"
    },
    "is_transformed": true,
    "package": "",
    "password": false,
    "resource-id": "",
    "screen_hash": "071b58031136189080806dd2342be43b",
    "scrollable": false,
    "tag_name": "h1",
    "text": "This site can\u2019t be reached",
    "transformed": true,
    "width": 600,
    "x": 660,
    "y": 240
}