{
    "bounds": "[576,1592][742,1644]",
    "class": "android.widget.TextView",
    "enabled": true,
    "hash": "X+r6LHXSuW+9MjN0YtSY/A==\n",
    "height": 52,
    "hier_level": 2,
    "human_hash": "android.widget.TextView_X576_Y1592_W166_H52",
    "human_readable": "android.widget.TextView_576_1592_166_52_android.widget.TextView_ffffbfffb96d28210a206a20282028a08420cc2000012145bfffffffffffffff_2cd05994be74b2bb16972e1bd33895e3",
    "image_path": "MGYzNDRkMmE1ZGFhOGE3MmY2M2RjYTE2NGMxOWM1NDY.png",
    "index": "1",
    "is_transformed": true,
    "screen_hash": "5d5c2224a9825ae944320e7d2aa7d3fd",
    "tag_name": "android.widget.TextView",
    "text": "$150.00",
    "width": 166,
    "x": 576,
    "y": 1592
}