{
    "bounds": "[0,1543][1080,1862]",
    "checkable": false,
    "checked": false,
    "class": "android.view.ViewGroup",
    "clickable": false,
    "enabled": true,
    "focusable": false,
    "focused": false,
    "hash": "8CRDtWsRdv+NtfMYi8QYpg==\n",
    "height": 319,
    "hier_level": 30,
    "human_hash": "android.view.ViewGroup_X0_Y1543_W1080_H319",
    "human_readable": "android.view.ViewGroup_0_1543_1080_319_android.view.ViewGroup_ffffffffffffffffffffffff7fff07fc07fdffffffffffffffff6cff00010001_f3c79732a8a512bd2845c5b921559aca",
    "image_path": "MmE4MTM5MjU5ODVjMGY5ZjhkZTRmOTU0NjcyNmU3OGI.png",
    "index": "1",
    "is_transformed": true,
    "long-clickable": false,
    "password": false,
    "screen_hash": "f5fcd99d82045050701889154f7723ca",
    "scrollable": false,
    "selected": false,
    "tag_name": "android.view.ViewGroup",
    "text": "Chat on whatsapp Call us",
    "width": 1080,
    "x": 0,
    "y": 1543
}