{
    "bounds": "[541,178][1064,753]",
    "checkable": false,
    "checked": false,
    "class": "android.view.ViewGroup",
    "clickable": true,
    "content-desc": "product-grid-item-7",
    "enabled": true,
    "focusable": true,
    "focused": false,
    "hash": "iodEYuNCvoqVGwfmNcbDVw==\n",
    "height": 575,
    "hier_level": 26,
    "human_hash": "android.view.ViewGroup_X541_Y178_W523_H575",
    "human_readable": "android.view.ViewGroup_541_178_523_575_android.view.ViewGroup_ffff8605000003ff07fffffffffffffffff1fffbffffffff000300030003000f_88972877db428c7e61e6332591a6d85d",
    "image_path": "NWIxZWJjNDI5NmU3ZGQxNzQ5ZDE2MjVjNjZkYTM1NDk.png",
    "index": "1",
    "is_transformed": true,
    "long-clickable": false,
    "password": false,
    "screen_hash": "4579417349bd84751da424042ca7eb2c",
    "scrollable": false,
    "selected": false,
    "tag_name": "android.view.ViewGroup",
    "text": "DNK Green Tshirt $150.00",
    "width": 523,
    "x": 541,
    "y": 178
}