{
    "bounds": "[28,178][529,738]",
    "checkable": false,
    "checked": false,
    "class": "android.view.ViewGroup",
    "clickable": false,
    "enabled": true,
    "focusable": false,
    "focused": false,
    "hash": "HC3YJjg2eGVAmUgBNGtz/g==\n",
    "height": 560,
    "hier_level": 27,
    "human_hash": "android.view.ViewGroup_X28_Y178_W501_H560",
    "human_readable": "android.view.ViewGroup_28_178_501_560_android.view.ViewGroup_ffffffff01ff23ffffffffff00000c31ffffffff3fff0007ffffffff34e80000_44daa667e4f0be4727dfb35df01d2729",
    "image_path": "ZDYzNGIyOGJhYjkyM2IxYzUwZDgwNzg4NjZlZDhmMzM.png",
    "index": "0",
    "is_transformed": true,
    "long-clickable": false,
    "password": false,
    "screen_hash": "329c47e355294d815a44f7b6035112bc",
    "scrollable": false,
    "selected": false,
    "tag_name": "android.view.ViewGroup",
    "text": "DNK Green Shoes $150.00",
    "width": 501,
    "x": 28,
    "y": 178
}