{
    "bounds": "[540,1934][810,2106]",
    "checkable": false,
    "checked": false,
    "class": "android.view.View",
    "clickable": true,
    "content-desc": "Wishlist",
    "enabled": true,
    "focusable": true,
    "focused": false,
    "hash": "7TRyhHYH06IWNqOmzMsrRw==\n",
    "height": 172,
    "hier_level": 26,
    "human_hash": "android.view.View_X540_Y1934_W270_H172",
    "human_readable": "android.view.View_540_1934_270_172_android.view.View_e001e000e000e000f000f000f803fc03ff87ffefffffffffffffffffffffffff_fdd5c4153058095065d63a0bf190d61a",
    "image_path": "ZWMzNGM5NzkyYzIxM2JmYTAxMjdiYWVlMjQ2MWI0NzU.png",
    "index": "2",
    "is_transformed": true,
    "long-clickable": false,
    "password": false,
    "screen_hash": "b27d11fa515491efb272cbf93c9dda9b",
    "scrollable": false,
    "selected": false,
    "tag_name": "android.view.View",
    "text": "WISHLIST",
    "width": 270,
    "x": 540,
    "y": 1934
}