{
    "bounds": "[0,1340][419,1835]",
    "checkable": false,
    "checked": false,
    "class": "android.widget.ImageView",
    "clickable": false,
    "enabled": true,
    "focusable": false,
    "focused": false,
    "hash": "mueDsdbxQ4Nk+ib40501ZA==\n",
    "height": 495,
    "hier_level": 32,
    "human_hash": "android.widget.ImageView_X0_Y1340_W419_H495",
    "human_readable": "android.widget.ImageView_0_1340_419_495_android.widget.ImageView_ffffffffffffffffffcff00f600f000307033003801fff03ffffffffffffffff_9d4568c009d203ab10e33ea9953a0264",
    "image_path": "MDMwZDE1N2Y2YWM0MjVjYTUxN2MxZjk1MjI5YzdiZjA.png",
    "index": "0",
    "is_transformed": true,
    "long-clickable": false,
    "password": false,
    "screen_hash": "067d3472de2bd3ca6eccaf249c2618ef",
    "scrollable": false,
    "selected": false,
    "tag_name": "android.widget.ImageView",
    "text": "",
    "width": 419,
    "x": 0,
    "y": 1340
}