{
    "bounds": "[193,324][737,392]",
    "checkable": false,
    "checked": false,
    "class": "android.widget.TextView",
    "clickable": false,
    "enabled": true,
    "focusable": false,
    "focused": false,
    "hash": "WRnG3VRBVK0zr3wdG9Z6GA==\n",
    "height": 68,
    "hier_level": 27,
    "human_hash": "android.widget.TextView_X193_Y324_W544_H68",
    "human_readable": "android.widget.TextView_193_324_544_68_android.widget.TextView_fffffffffffffffff2ff537f737f001f001f001f003f001f003f94ff94ffffff_4d18b6f984c8330bcbca13ff5648ffec",
    "image_path": "Y2U3NmRiYTQzNjE5MzFiMjI2Y2NiYWNjZTEyY2VhODM.png",
    "index": "0",
    "is_transformed": true,
    "long-clickable": false,
    "password": false,
    "screen_hash": "3df714b87bc57e583c87e08628e27d18",
    "scrollable": false,
    "selected": false,
    "tag_name": "android.widget.TextView",
    "text": "Login | Register",
    "width": 544,
    "x": 193,
    "y": 324
}