{
    "behavior": "",
    "checkable": false,
    "class": "label",
    "clickable": true,
    "content-desc": "",
    "enabled": true,
    "focusable": true,
    "focused": false,
    "hash": "FKhDBurhGFmQ/DihGMmCfg==\n",
    "height": 24,
    "hier_level": 0,
    "human_hash": "label_X1124_Y559_W41_H24",
    "human_readable": "label_1124_559_41_24_label_ffffffffffffffef1f8f4f9f410940001886108644004109ffffffffffffffff_f6ced244918bcbe32cfbeb4ddf63af5f",
    "image_path": "MGU5MDk5ODEyOWQ3YWExMzk3ODM0NTEyNmY5ZDA4ZDk.png",
    "index": -1,
    "internal": {
        "elem_dict": {
            "attributes": {
                "class": "custom-control-label",
                "for": "customRadio2"
            },
            "backend_node_id": 709,
            "flags": {
                "checkable": false,
                "clickable": true,
                "enabled": true,
                "focusable": true,
                "focused": false,
                "scrollable": false
            },
            "height": 24.0,
            "key": "1124_559_41_24_Radio",
            "tagName": "label",
            "text": "Radio",
            "width": 41.0,
            "x": 1124.0,
            "y": 559.0
        },
        "location": {
            "x": 1124.0,
            "y": 559.0
        },
        "size": {
            "height": 24.0,
            "width": 41.0
        },
        "tag_name": "label",
        "text": "Radio"
    },
    "is_transformed": true,
    "package": "",
    "password": false,
    "resource-id": "",
    "screen_hash": "cdfa6571b1ecfb54d3f360f8806aa9c1",
    "scrollable": false,
    "tag_name": "label",
    "text": "Radio",
    "transformed": true,
    "width": 41,
    "x": 1124,
    "y": 559
}