{
    "behavior": "",
    "checkable": false,
    "class": "p",
    "clickable": true,
    "content-desc": "",
    "enabled": true,
    "focusable": true,
    "focused": false,
    "hash": "8sSw6INWftHoUGe/Es0C7A==\n",
    "height": 18,
    "hier_level": 0,
    "human_hash": "p_X660_Y289_W210_H18",
    "human_readable": "p_660_289_210_18_p_ffffffffffffffff67ff77fd0000000080808000000000000000ffdcffdfffdf_3f6848ff91ea481517c9599f20b9854f",
    "image_path": "MzExOGVlOWZmZWEwMGI3NTU3NDVlYjU5ZDBkZGExMWM.png",
    "index": -1,
    "internal": {
        "elem_dict": {
            "attributes": {
                "jsselect": "summary",
                "jstcache": "1",
                "jsvalues": ".innerHTML:msg"
            },
            "backend_node_id": 989,
            "flags": {
                "checkable": false,
                "clickable": true,
                "enabled": true,
                "focusable": true,
                "focused": false,
                "scrollable": false
            },
            "height": 18.0,
            "key": "660_289_210_18_Check if there is a typo in  http .",
            "tagName": "p",
            "text": "Check if there is a typo in  http .",
            "width": 210.0,
            "x": 660.0,
            "y": 289.0
        },
        "location": {
            "x": 660.0,
            "y": 289.0
        },
        "size": {
            "height": 18.0,
            "width": 210.0
        },
        "tag_name": "p",
        "text": "Check if there is a typo in  http ."
    },
    "is_transformed": true,
    "package": "",
    "password": false,
    "resource-id": "",
    "screen_hash": "071b58031136189080806dd2342be43b",
    "scrollable": false,
    "tag_name": "p",
    "text": "Check if there is a typo in  http .",
    "transformed": true,
    "width": 210,
    "x": 660,
    "y": 289
}