{
    "behavior": "",
    "checkable": false,
    "class": "h2",
    "clickable": true,
    "content-desc": "",
    "enabled": true,
    "focusable": true,
    "focused": false,
    "hash": "2cO9EgufkjG2RLl1BqI6Ew==\n",
    "height": 38,
    "hier_level": 0,
    "human_hash": "h2_X42_Y88_W450_H38",
    "human_readable": "h2_42_88_450_38_h2_0000c000c000c000e400e000fc00be00bc00fc00fc00fe00fe00e000a0000000_8304eaaff0002ec47c5ecde56bcbd250",
    "image_path": "NmFmOGVjNTUwN2ZjNDBlMGU1Njg3YTJjZmU5Njk2ZmM.png",
    "index": -1,
    "internal": {
        "elem_dict": {
            "attributes": {},
            "backend_node_id": 1041,
            "flags": {
                "checkable": false,
                "clickable": true,
                "enabled": true,
                "focusable": true,
                "focused": false,
                "scrollable": false
            },
            "height": 38.0,
            "key": "42_88_450_38_Dynamic",
            "tagName": "h2",
            "text": "Dynamic",
            "width": 450.0,
            "x": 42.0,
            "y": 88.0
        },
        "location": {
            "x": 42.0,
            "y": 88.0
        },
        "size": {
            "height": 38.0,
            "width": 450.0
        },
        "tag_name": "h2",
        "text": "Dynamic"
    },
    "is_transformed": true,
    "package": "",
    "password": false,
    "resource-id": "",
    "screen_hash": "6b9a481c2115691c103b0466c903a2fc",
    "scrollable": false,
    "tag_name": "h2",
    "text": "Dynamic",
    "transformed": true,
    "width": 450,
    "x": 42,
    "y": 88
}