{
    "behavior": "",
    "checkable": false,
    "class": "li",
    "clickable": true,
    "content-desc": "",
    "enabled": true,
    "focusable": true,
    "focused": false,
    "hash": "ZWswWDOukeRkeFZCsRE9hw==\n",
    "height": 40,
    "hier_level": 0,
    "human_hash": "li_X1674_Y8_W141_H40",
    "human_readable": "li_1674_8_141_40_li_0000000000000000000021007fec7ffc7dfc7ffe3ffc00000000000000000000_8696dcb9da2c2189653ede03c73c8390",
    "image_path": "NTJmZWUwOWU2OTNhMTE5NzE0NTNhNTBiN2M1OWRkYjQ.png",
    "index": -1,
    "internal": {
        "elem_dict": {
            "attributes": {
                "class": "nav-item px-2"
            },
            "backend_node_id": 1193,
            "flags": {
                "checkable": false,
                "clickable": true,
                "enabled": true,
                "focusable": true,
                "focused": false,
                "scrollable": false
            },
            "height": 40.0,
            "key": "1674_8_141_40_Basic Gestures",
            "tagName": "li",
            "text": "Basic Gestures",
            "width": 141.0,
            "x": 1674.0,
            "y": 8.0
        },
        "location": {
            "x": 1674.0,
            "y": 8.0
        },
        "size": {
            "height": 40.0,
            "width": 141.0
        },
        "tag_name": "li",
        "text": "Basic Gestures"
    },
    "is_transformed": true,
    "package": "",
    "password": false,
    "resource-id": "",
    "screen_hash": "5e67e96d1fd09af8370705518e552c7e",
    "scrollable": false,
    "tag_name": "li",
    "text": "Basic Gestures",
    "transformed": true,
    "width": 141,
    "x": 1674,
    "y": 8
}