{
    "behavior": "",
    "checkable": false,
    "class": "div",
    "clickable": true,
    "content-desc": "",
    "enabled": true,
    "focusable": true,
    "focused": false,
    "hash": "uxrBI7wWUycWRhlrdIqd1Q==\n",
    "height": 574,
    "hier_level": 0,
    "human_hash": "div_X405_Y214_W1110_H574",
    "human_readable": "div_405_214_1110_574_div_00000000bfff0ffd0fffffffffffbffdffffce73ce73bfff9fff9fff9fff9fff_0e2d527d350bcea468fbfe2fb7cea4c8",
    "image_path": "ZGVjMzQyMTZmMDMwZGJjY2ZhOTc3MWU5OTUxNzc4YWY.png",
    "index": -1,
    "internal": {
        "elem_dict": {
            "attributes": {
                "class": "card"
            },
            "backend_node_id": 919,
            "flags": {
                "checkable": false,
                "clickable": true,
                "enabled": true,
                "focusable": true,
                "focused": false,
                "scrollable": false
            },
            "height": 574.0,
            "key": "405_214_1110_574_DYNAMIC TESTING INFO  Change Next Confirm Toggle One  Toggle Two  Toggle Three",
            "tagName": "div",
            "text": "DYNAMIC TESTING INFO  Change Next Confirm Toggle One  Toggle Two  Toggle Three",
            "width": 1110.0,
            "x": 405.0,
            "y": 214.0
        },
        "location": {
            "x": 405.0,
            "y": 214.0
        },
        "size": {
            "height": 574.0,
            "width": 1110.0
        },
        "tag_name": "div",
        "text": "DYNAMIC TESTING INFO  Change Next Confirm Toggle One  Toggle Two  Toggle Three"
    },
    "is_transformed": true,
    "package": "",
    "password": false,
    "resource-id": "",
    "screen_hash": "1d085165454efe7fa67ab037f179d6e5",
    "scrollable": false,
    "tag_name": "div",
    "text": "DYNAMIC TESTING INFO  Change Next Confirm Toggle One  Toggle Two  Toggle Three",
    "transformed": true,
    "width": 1110,
    "x": 405,
    "y": 214
}