{
    "behavior": "",
    "checkable": false,
    "class": "textarea",
    "clickable": true,
    "content-desc": "",
    "enabled": true,
    "focusable": true,
    "focused": false,
    "hash": "Yx06LzPgbIlojfUFFN+dBQ==\n",
    "height": 134,
    "hier_level": 0,
    "human_hash": "textarea_X442_Y345_W1036_H134",
    "human_readable": "textarea_442_345_1036_134_textarea_00007fff3fff7fffffffffffffffffffffffffffffffffffffffffffffff0000_1a808aba267dc82866aa54df45cc617c",
    "image_path": "ZmU4ZmM3YTBlZjk0MWQyMTQ4NWJlMWJlZjU3YzdlOGY.png",
    "index": -1,
    "internal": {
        "elem_dict": {
            "attributes": {
                "class": "form-control",
                "id": "eleminfo-area",
                "name": "name",
                "placeholder": "",
                "rows": "5",
                "value": "button"
            },
            "backend_node_id": 365,
            "flags": {
                "checkable": false,
                "clickable": true,
                "enabled": true,
                "focusable": true,
                "focused": false,
                "scrollable": false
            },
            "height": 134.0,
            "key": "442_345_1036_134_",
            "tagName": "textarea",
            "text": "",
            "width": 1036.0,
            "x": 442.0,
            "y": 345.0
        },
        "location": {
            "x": 442.0,
            "y": 345.0
        },
        "size": {
            "height": 134.0,
            "width": 1036.0
        },
        "tag_name": "textarea",
        "text": ""
    },
    "is_transformed": true,
    "package": "",
    "password": false,
    "resource-id": "",
    "screen_hash": "411271a8075619a41c4ff1857f8429e7",
    "scrollable": false,
    "tag_name": "textarea",
    "text": "button",
    "transformed": true,
    "width": 1036,
    "x": 442,
    "y": 345
}